README.md
setup.py
HexColors.egg-info/PKG-INFO
HexColors.egg-info/SOURCES.txt
HexColors.egg-info/dependency_links.txt
HexColors.egg-info/top_level.txt
hexcolors/__init__.py
hexcolors/colors.py