Metadata-Version: 2.1
Name: HexColors
Version: 0.0.2
Summary: Organized Hex Color Tuples
Home-page: https://gitlab.com/Reggles44/hex-colors
Author: Reggles
Author-email: reginaldbeakes@gmail.com
License: UNKNOWN
Platform: UNKNOWN
Classifier: Programming Language :: Python :: 3
Classifier: Operating System :: OS Independent
